setup.py
Async_single/Async.py
Async_single/__init__.py
Async_single.egg-info/PKG-INFO
Async_single.egg-info/SOURCES.txt
Async_single.egg-info/dependency_links.txt
Async_single.egg-info/entry_points.txt
Async_single.egg-info/top_level.txt