Metadata-Version: 1.0
Name: Async-single
Version: 0.1
Summary: python Async_single
Home-page: UNKNOWN
Author: nbl
Author-email: UNKNOWN
License: UNKNOWN
Platform: UNKNOWN
